timm/__init__.py
timm/version.py
timm/data/__init__.py
timm/data/auto_augment.py
timm/data/config.py
timm/data/constants.py
timm/data/dataset.py
timm/data/dataset_factory.py
timm/data/dataset_info.py
timm/data/distributed_sampler.py
timm/data/imagenet_info.py
timm/data/loader.py
timm/data/mixup.py
timm/data/random_erasing.py
timm/data/real_labels.py
timm/data/tf_preprocessing.py
timm/data/transforms.py
timm/data/transforms_factory.py
timm/data/_info/imagenet12k_synsets.txt
timm/data/_info/imagenet21k_goog_synsets.txt
timm/data/_info/imagenet21k_goog_to_12k_indices.txt
timm/data/_info/imagenet21k_goog_to_22k_indices.txt
timm/data/_info/imagenet21k_miil_synsets.txt
timm/data/_info/imagenet21k_miil_w21_synsets.txt
timm/data/_info/imagenet22k_ms_synsets.txt
timm/data/_info/imagenet22k_ms_to_12k_indices.txt
timm/data/_info/imagenet22k_ms_to_22k_indices.txt
timm/data/_info/imagenet22k_synsets.txt
timm/data/_info/imagenet22k_to_12k_indices.txt
timm/data/_info/imagenet_a_indices.txt
timm/data/_info/imagenet_a_synsets.txt
timm/data/_info/imagenet_r_indices.txt
timm/data/_info/imagenet_r_synsets.txt
timm/data/_info/imagenet_real_labels.json
timm/data/_info/imagenet_synset_to_definition.txt
timm/data/_info/imagenet_synset_to_lemma.txt
timm/data/_info/imagenet_synsets.txt
timm/data/readers/__init__.py
timm/data/readers/class_map.py
timm/data/readers/img_extensions.py
timm/data/readers/reader.py
timm/data/readers/reader_factory.py
timm/data/readers/reader_hfds.py
timm/data/readers/reader_hfids.py
timm/data/readers/reader_image_folder.py
timm/data/readers/reader_image_in_tar.py
timm/data/readers/reader_image_tar.py
timm/data/readers/reader_tfds.py
timm/data/readers/reader_wds.py
timm/data/readers/shared_count.py
timm/layers/__init__.py
timm/layers/activations.py
timm/layers/activations_jit.py
timm/layers/activations_me.py
timm/layers/adaptive_avgmax_pool.py
timm/layers/attention_pool.py
timm/layers/attention_pool2d.py
timm/layers/blur_pool.py
timm/layers/bottleneck_attn.py
timm_eidl-0.9.14.dev0.dist-info/LICENSE
timm_eidl-0.9.14.dev0.dist-info/METADATA
timm_eidl-0.9.14.dev0.dist-info/WHEEL
timm_eidl-0.9.14.dev0.dist-info/top_level.txt
timm_eidl-0.9.14.dev0.dist-info/RECORD
