Metadata-Version: 2.1
Name: timm-eidl
Version: 0.9.14.dev0
Summary: PyTorch Image Models
Home-page: https://github.com/huggingface/pytorch-image-models
Author: Ross Wightman
Author-email: ross@huggingface.co
Keywords: pytorch pretrained models efficientnet mobilenetv3 mnasnet resnet vision transformer vit
Classifier: Development Status :: 4 - Beta
Classifier: Intended Audience :: Education
Classifier: Intended Audience :: Science/Research
Classifier: License :: OSI Approved :: Apache Software License
Classifier: Programming Language :: Python :: 3.8
Classifier: Programming Language :: Python :: 3.9
Classifier: Programming Language :: Python :: 3.10
Classifier: Programming Language :: Python :: 3.11
Classifier: Topic :: Scientific/Engineering
Classifier: Topic :: Scientific/Engineering :: Artificial Intelligence
Classifier: Topic :: Software Development
Classifier: Topic :: Software Development :: Libraries
Classifier: Topic :: Software Development :: Libraries :: Python Modules
Requires-Python: >=3.7
License-File: LICENSE
Requires-Dist: torch >=1.7
Requires-Dist: torchvision
Requires-Dist: pyyaml
Requires-Dist: huggingface-hub
Requires-Dist: safetensors
